apis_override_select2js/__init__.py
apis_override_select2js/apps.py
apis_override_select2js/static/autocomplete_light/select2.js
apis_override_select2js/static/autocomplete_light/select2.min.js
apis_override_select2js-0.2.1.dist-info/METADATA
apis_override_select2js-0.2.1.dist-info/WHEEL
apis_override_select2js-0.2.1.dist-info/RECORD
